opsys_ps_controller/__init__.py
opsys_ps_controller/ps_abstract.py
opsys_ps_controller/ps_configs.py
opsys_ps_controller/ps_controller.py
opsys_ps_controller/tdk_z_controller.py
opsys_ps_controller/tdk_zup_controller.py
opsys_ps_controller-0.0.8.dist-info/LICENSE
opsys_ps_controller-0.0.8.dist-info/METADATA
opsys_ps_controller-0.0.8.dist-info/WHEEL
opsys_ps_controller-0.0.8.dist-info/top_level.txt
opsys_ps_controller-0.0.8.dist-info/RECORD
