Metadata-Version: 2.1
Name: opsys-ps-controller
Version: 0.0.8
Summary: python package for power supply device control
Home-page: https://bitbucket.org/opsys_tech/opsys-ps-controller/src/master/
Download-URL: https://bitbucket.org/opsys_tech/opsys-ps-controller/src/master/
Author: dmitry.borovensky
Author-email: dmitry.borovensky@opsys-tech.com
License-File: LICENSE
